tartiflette_asgi/__init__.py
tartiflette_asgi/_app.py
tartiflette_asgi/_datastructures.py
tartiflette_asgi/_endpoints.py
tartiflette_asgi/_errors.py
tartiflette_asgi/_middleware.py
tartiflette_asgi/graphiql.html
tartiflette_asgi/py.typed
tartiflette_asgi/_subscriptions/__init__.py
tartiflette_asgi/_subscriptions/constants.py
tartiflette_asgi/_subscriptions/impl.py
tartiflette_asgi/_subscriptions/protocol.py
tartiflette_asgi-0.12.0.dist-info/LICENSE
tartiflette_asgi-0.12.0.dist-info/METADATA
tartiflette_asgi-0.12.0.dist-info/WHEEL
tartiflette_asgi-0.12.0.dist-info/top_level.txt
tartiflette_asgi-0.12.0.dist-info/RECORD
