Metadata-Version: 2.1
Name: tartiflette-asgi
Version: 0.12.0
Summary: ASGI support for the Tartiflette Python GraphQL engine
Home-page: https://github.com/tartiflette/tartiflette-asgi
Author: Florimond Manca
Author-email: florimond.manca@gmail.com
License: MIT
Platform: UNKNOWN
Classifier: Development Status :: 4 - Beta
Classifier: Operating System :: OS Independent
Classifier: Intended Audience :: Developers
Classifier: Topic :: Software Development :: Libraries
Classifier: Programming Language :: Python :: 3 :: Only
Classifier: Programming Language :: Python :: 3.6
Classifier: Programming Language :: Python :: 3.7
Classifier: Programming Language :: Python :: 3.8
Classifier: Programming Language :: Python :: 3.9
Classifier: Programming Language :: Python :: 3.10
Requires-Python: >=3.6
License-File: LICENSE
Requires-Dist: starlette (<1.0,>=0.13)
Requires-Dist: tartiflette (<1.5,>=1.0)
Requires-Dist: typing-extensions ; python_version < "3.8"
